README.rst
setup.cfg
setup.py
pyramid_secure_response/__init__.py
pyramid_secure_response/csp_coverage.py
pyramid_secure_response/hsts_support.py
pyramid_secure_response/ssl_redirect.py
pyramid_secure_response/util.py
pyramid_secure_response.egg-info/PKG-INFO
pyramid_secure_response.egg-info/SOURCES.txt
pyramid_secure_response.egg-info/dependency_links.txt
pyramid_secure_response.egg-info/not-zip-safe
pyramid_secure_response.egg-info/requires.txt
pyramid_secure_response.egg-info/top_level.txt
test/__init__.py
test/conftest.py
test/unit/__init__.py
test/unit/csp_coverage_test.py
test/unit/hsts_support_test.py
test/unit/ssl_redirect_test.py
test/unit/util_test.py