Metadata-Version: 1.1
Name: pyramid-secure-response
Version: 0.1.1
Summary: A library redirects non-http as https, sets hsts header.
Home-page: https://gitlab.com/grauwoelfchen/pyramid_secure_response
Author: Yasuhiro Asaka
Author-email: yasuhiro.asaka@grauwoelfchen.net
License: BSD-3-Clause
Keywords: web wsgi pylons pyramid
Platform: UNKNOWN
Classifier: Development Status :: 4 - Beta
Classifier: Environment :: Web Environment
Classifier: Framework :: Pyramid
Classifier: Intended Audience :: Developers
Classifier: Programming Language :: Python :: 3
Classifier: Programming Language :: Python :: 2
Classifier: Topic :: Internet :: WWW/HTTP
Classifier: Topic :: Security
